timeseries/__init__.py
timeseries/controlchart.py
timeseries/general.py
timeseries/henderson.py
timeseries/linearregression.py
timeseries/rulesets.py
timeseries/seasonal.py
timeseries/segment.py
va_timeseries-1.0.7.dist-info/LICENSE.txt
va_timeseries-1.0.7.dist-info/METADATA
va_timeseries-1.0.7.dist-info/WHEEL
va_timeseries-1.0.7.dist-info/top_level.txt
va_timeseries-1.0.7.dist-info/RECORD
