Metadata-Version: 2.1
Name: va-timeseries
Version: 1.0.7
Summary: Timeseries Analysis
Home-page: https://github.com/joocer/timeseries
Author: Joocer
Author-email: justin.joyce@joocer.com
License: UNKNOWN
Platform: UNKNOWN
Requires-Dist: pandas
Requires-Dist: matplotlib
Requires-Dist: numpy
